localtrans/__init__.py
localtrans/configuration.py
localtrans/models/__init__.py
localtrans/models/exceptions.py
localtrans/models/pytranslator.py
localtrans/translator.py
localtrans-0.1.2.dist-info/METADATA
localtrans-0.1.2.dist-info/WHEEL
localtrans-0.1.2.dist-info/RECORD
