Metadata-Version: 2.1
Name: localtrans
Version: 0.1.2
Summary: 
Author: Oğuz Yeşil
Author-email: oguzyesil17@gmail.com
Requires-Python: >=3.10,<4.0
Classifier: Programming Language :: Python :: 3
Classifier: Programming Language :: Python :: 3.10
Classifier: Programming Language :: Python :: 3.11
Classifier: Programming Language :: Python :: 3.12
Requires-Dist: faker (>=26.1.0,<27.0.0)
Requires-Dist: pydantic (>=2.8.2,<3.0.0)
Requires-Dist: pytest (>=8.3.2,<9.0.0)
